LICENSE
MANIFEST.in
README.rst
setup.py
bls/__init__.py
bls/_impl.pyx
bls/bls.c
bls/core.py
bls/methods.py
bls/setup_package.py
bls.py.egg-info/PKG-INFO
bls.py.egg-info/SOURCES.txt
bls.py.egg-info/dependency_links.txt
bls.py.egg-info/top_level.txt