Metadata-Version: 1.0
Name: bls.py
Version: 0.1.2
Summary: A reference implementation of box least squares in Python
Home-page: https://github.com/dfm/bls.py
Author: Daniel Foreman-Mackey & Ze Vinicius
Author-email: foreman.mackey@gmail.com
License: BSD
Platform: UNKNOWN
